gget/__init__.py
gget/__main__.py
gget/compile.py
gget/constants.py
gget/gget_alphafold.py
gget/gget_archs4.py
gget/gget_bgee.py
gget/gget_blast.py
gget/gget_blat.py
gget/gget_cbio.py
gget/gget_cellxgene.py
gget/gget_cosmic.py
gget/gget_diamond.py
gget/gget_elm.py
gget/gget_enrichr.py
gget/gget_gpt.py
gget/gget_info.py
gget/gget_muscle.py
gget/gget_mutate.py
gget/gget_opentargets.py
gget/gget_pdb.py
gget/gget_ref.py
gget/gget_search.py
gget/gget_seq.py
gget/gget_setup.py
gget/main.py
gget/utils.py
gget/bins/Darwin/diamond
gget/bins/Darwin/jackhmmer
gget/bins/Darwin/license.txt
gget/bins/Darwin/muscle
gget/bins/Linux/diamond
gget/bins/Linux/jackhmmer
gget/bins/Linux/license.txt
gget/bins/Linux/muscle
gget/bins/Windows/diamond.exe
gget/bins/Windows/license.txt
gget/bins/Windows/muscle.win64.exe
gget/bins/alphafold/LICENSE
gget/bins/alphafold/NOTICE
gget/bins/alphafold/stereo_chemical_props.txt
gget/constants/enrichr_bkg_genes.txt
gget-0.29.3.dist-info/LICENSE
gget-0.29.3.dist-info/METADATA
gget-0.29.3.dist-info/WHEEL
gget-0.29.3.dist-info/entry_points.txt
gget-0.29.3.dist-info/top_level.txt
gget-0.29.3.dist-info/RECORD
