Metadata-Version: 2.1
Name: gget
Version: 0.29.3
Summary: Efficient querying of genomic databases.
Home-page: https://github.com/pachterlab/gget
Author: Laura Luebbert
Author-email: lauralubbert@gmail.com
Maintainer: Laura Luebbert
Maintainer-email: lauralubbert@gmail.com
License: BSD-2
Keywords: gget
Classifier: Environment :: Console
Classifier: Framework :: Jupyter
Classifier: Intended Audience :: Science/Research
Classifier: License :: OSI Approved :: BSD License
Classifier: Operating System :: OS Independent
Classifier: Programming Language :: Python :: 3.7
Classifier: Programming Language :: Python :: 3.8
Classifier: Programming Language :: Python :: 3.9
Classifier: Programming Language :: Python :: 3.10
Classifier: Programming Language :: Python :: 3.11
Classifier: Programming Language :: Python :: 3.12
Classifier: Topic :: Scientific/Engineering :: Bio-Informatics
Classifier: Topic :: Utilities
Requires-Python: >=3.7
License-File: LICENSE
Requires-Dist: numpy>=1.17.2
Requires-Dist: pandas>=1.0.0
Requires-Dist: requests>=2.22.0
Requires-Dist: ipython
Requires-Dist: matplotlib
Requires-Dist: mysql-connector-python>=8.0.32
Requires-Dist: beautifulsoup4>=4.10.0
Requires-Dist: ipywidgets
Requires-Dist: tqdm
Requires-Dist: lxml
